{
  "db_name": "SQLite",
  "query": "\n\t\t\t\tSELECT log_index, address, transaction_hash, topic_0, topic_1, topic_2, topic_3, data\n\t\t\t\tFROM logs\n\t\t\t\tWHERE block_hash = $1 AND transaction_index = $2\n\t\t\t\tORDER BY log_index ASC\n\t\t\t\t",
  "describe": {
    "columns": [
      {
        "name": "log_index",
        "ordinal": 0,
        "type_info": "Integer"
      },
      {
        "name": "address",
        "ordinal": 1,
        "type_info": "Blob"
      },
      {
        "name": "transaction_hash",
        "ordinal": 2,
        "type_info": "Blob"
      },
      {
        "name": "topic_0",
        "ordinal": 3,
        "type_info": "Blob"
      },
      {
        "name": "topic_1",
        "ordinal": 4,
        "type_info": "Blob"
      },
      {
        "name": "topic_2",
        "ordinal": 5,
        "type_info": "Blob"
      },
      {
        "name": "topic_3",
        "ordinal": 6,
        "type_info": "Blob"
      },
      {
        "name": "data",
        "ordinal": 7,
        "type_info": "Blob"
      }
    ],
    "parameters": {
      "Right": 2
    },
    "nullable": [
      false,
      false,
      false,
      true,
      true,
      true,
      true,
      true
    ]
  },
  "hash": "ef3f837bd2088904f6e4c258a32512b1d39982bade66f588600c4a3816eb426c"
}
